[{"rank":1,"name":"zob","brawlhalla_id":97562336,"best_legend":40,"best_legend_games":247,"best_legend_wins":182,"rating":2649,"tier":"Valhallan","games":247,"wins":182,"region":"EU","peak_rating":2649},{"rank":2,"name":"rikka","brawlhalla_id":6193054,"best_legend":35,"best_legend_games":598,"best_legend_wins":401,"rating":2646,"tier":"Valhallan","games":598,"wins":401,"region":"EU","peak_rating":2658},{"rank":3,"name":"T.TV/SHAWBH LIVE NOW","brawlhalla_id":395872,"best_legend":15,"best_legend_games":438,"best_legend_wins":296,"rating":2631,"tier":"Valhallan","games":438,"wins":296,"region":"EU","peak_rating":2662},{"rank":4,"name":"KC | Pierchy","brawlhalla_id":10241375,"best_legend":54,"best_legend_games":591,"best_legend_wins":383,"rating":2603,"tier":"Valhallan","games":591,"wins":383,"region":"EU","peak_rating":2603},{"rank":5,"name":"vshq","brawlhalla_id":31376067,"best_legend":20,"best_legend_games":365,"best_legend_wins":220,"rating":2602,"tier":"Valhallan","games":365,"wins":220,"region":"EU","peak_rating":2602},{"rank":6,"name":"TheYeahGuy","brawlhalla_id":51473222,"best_legend":53,"best_legend_games":1087,"best_legend_wins":655,"rating":2600,"tier":"Valhallan","games":1087,"wins":655,"region":"EU","peak_rating":2600},{"rank":7,"name":"KD | xJcoolJ","brawlhalla_id":73041583,"best_legend":44,"best_legend_games":252,"best_legend_wins":165,"rating":2600,"tier":"Valhallan","games":252,"wins":165,"region":"EU","peak_rating":2600},{"rank":8,"name":"Machèèèèté","brawlhalla_id":200122,"best_legend":61,"best_legend_games":385,"best_legend_wins":256,"rating":2597,"tier":"Valhallan","games":385,"wins":256,"region":"EU","peak_rating":2597},{"rank":9,"name":"Saphir","brawlhalla_id":70129836,"best_legend":22,"best_legend_games":556,"best_legend_wins":350,"rating":2595,"tier":"Valhallan","games":556,"wins":350,"region":"EU","peak_rating":2617},{"rank":10,"name":"KC | Ra1n","brawlhalla_id":7838302,"best_legend":30,"best_legend_games":417,"best_legend_wins":266,"rating":2585,"tier":"Valhallan","games":417,"wins":266,"region":"EU","peak_rating":2617},{"rank":11,"name":"Kurisu Makise \u003c3","brawlhalla_id":173537,"best_legend":16,"best_legend_games":369,"best_legend_wins":230,"rating":2576,"tier":"Valhallan","games":369,"wins":230,"region":"EU","peak_rating":2576},{"rank":12,"name":"KC | RayzoX","brawlhalla_id":93709796,"best_legend":16,"best_legend_games":175,"best_legend_wins":118,"rating":2566,"tier":"Valhallan","games":175,"wins":118,"region":"EU","peak_rating":2566},{"rank":13,"name":"VEN | (mini fezaru80) alessia \u003c","brawlhalla_id":108122981,"best_legend":36,"best_legend_games":710,"best_legend_wins":377,"rating":2565,"tier":"Valhallan","games":710,"wins":377,"region":"EU","peak_rating":2601},{"rank":14,"name":"KD acno?","brawlhalla_id":2768493,"best_legend":3,"best_legend_games":200,"best_legend_wins":145,"rating":2565,"tier":"Valhallan","games":200,"wins":145,"region":"EU","peak_rating":2585},{"rank":15,"name":"Crazy Cow 002754","brawlhalla_id":68924836,"best_legend":50,"best_legend_games":138,"best_legend_wins":107,"rating":2552,"tier":"Valhallan","games":138,"wins":107,"region":"EU","peak_rating":2552},{"rank":16,"name":"M30W | Marker","brawlhalla_id":73088088,"best_legend":30,"best_legend_games":348,"best_legend_wins":224,"rating":2550,"tier":"Valhallan","games":348,"wins":224,"region":"EU","peak_rating":2557},{"rank":17,"name":"Djessir","brawlhalla_id":40375990,"best_legend":16,"best_legend_games":152,"best_legend_wins":104,"rating":2549,"tier":"Valhallan","games":152,"wins":104,"region":"EU","peak_rating":2556},{"rank":18,"name":"Sarme","brawlhalla_id":6049888,"best_legend":35,"best_legend_games":319,"best_legend_wins":218,"rating":2542,"tier":"Valhallan","games":319,"wins":218,"region":"EU","peak_rating":2566},{"rank":19,"name":"Sgrape","brawlhalla_id":6746620,"best_legend":5,"best_legend_games":332,"best_legend_wins":227,"rating":2541,"tier":"Valhallan","games":332,"wins":227,"region":"EU","peak_rating":2571},{"rank":20,"name":"EL TORO COMBO MEAL","brawlhalla_id":41855064,"best_legend":29,"best_legend_games":257,"best_legend_wins":157,"rating":2539,"tier":"Valhallan","games":257,"wins":157,"region":"EU","peak_rating":2546},{"rank":21,"name":"Jay Cutler","brawlhalla_id":37953369,"best_legend":35,"best_legend_games":504,"best_legend_wins":290,"rating":2537,"tier":"Valhallan","games":504,"wins":290,"region":"EU","peak_rating":2537},{"rank":22,"name":"anubis","brawlhalla_id":77331437,"best_legend":54,"best_legend_games":521,"best_legend_wins":325,"rating":2527,"tier":"Valhallan","games":521,"wins":325,"region":"EU","peak_rating":2527},{"rank":23,"name":"Paganini","brawlhalla_id":3970250,"best_legend":36,"best_legend_games":56,"best_legend_wins":49,"rating":2527,"tier":"Diamond","games":56,"wins":49,"region":"EU","peak_rating":2527},{"rank":24,"name":"KD | FryDasOle","brawlhalla_id":281816,"best_legend":48,"best_legend_games":529,"best_legend_wins":331,"rating":2526,"tier":"Valhallan","games":529,"wins":331,"region":"EU","peak_rating":2552},{"rank":25,"name":"KNKI|TBS","brawlhalla_id":30951797,"best_legend":12,"best_legend_games":733,"best_legend_wins":399,"rating":2523,"tier":"Valhallan","games":733,"wins":399,"region":"EU","peak_rating":2545},{"rank":26,"name":"KC | FXL","brawlhalla_id":44697675,"best_legend":48,"best_legend_games":123,"best_legend_wins":94,"rating":2523,"tier":"Diamond","games":123,"wins":94,"region":"EU","peak_rating":2523},{"rank":27,"name":"TheLeo","brawlhalla_id":10374431,"best_legend":18,"best_legend_games":1000,"best_legend_wins":610,"rating":2519,"tier":"Valhallan","games":1000,"wins":610,"region":"EU","peak_rating":2558},{"rank":28,"name":"Clockwork","brawlhalla_id":1000855,"best_legend":13,"best_legend_games":1909,"best_legend_wins":1211,"rating":2518,"tier":"Valhallan","games":1909,"wins":1211,"region":"EU","peak_rating":2613},{"rank":29,"name":"J44l","brawlhalla_id":95502500,"best_legend":16,"best_legend_games":376,"best_legend_wins":248,"rating":2516,"tier":"Valhallan","games":376,"wins":248,"region":"EU","peak_rating":2539},{"rank":30,"name":"sage","brawlhalla_id":69630716,"best_legend":30,"best_legend_games":592,"best_legend_wins":349,"rating":2515,"tier":"Valhallan","games":592,"wins":349,"region":"EU","peak_rating":2551},{"rank":31,"name":"HX","brawlhalla_id":49936771,"best_legend":31,"best_legend_games":291,"best_legend_wins":185,"rating":2514,"tier":"Valhallan","games":291,"wins":185,"region":"EU","peak_rating":2546},{"rank":32,"name":"TheNinja729 - #Bulbizarre","brawlhalla_id":376629,"best_legend":64,"best_legend_games":225,"best_legend_wins":150,"rating":2509,"tier":"Valhallan","games":225,"wins":150,"region":"EU","peak_rating":2543},{"rank":33,"name":"wg,qawsewe\u003cget\u003c","brawlhalla_id":23837364,"best_legend":35,"best_legend_games":628,"best_legend_wins":372,"rating":2508,"tier":"Valhallan","games":628,"wins":372,"region":"EU","peak_rating":2508},{"rank":34,"name":"PCS | Shadra - Baguette senpai","brawlhalla_id":7159263,"best_legend":33,"best_legend_games":269,"best_legend_wins":165,"rating":2506,"tier":"Valhallan","games":269,"wins":165,"region":"EU","peak_rating":2534},{"rank":35,"name":"KD | Godly","brawlhalla_id":5156845,"best_legend":16,"best_legend_games":36,"best_legend_wins":36,"rating":2505,"tier":"Diamond","games":36,"wins":36,"region":"EU","peak_rating":2505},{"rank":36,"name":"EVO Moment #37","brawlhalla_id":8095872,"best_legend":35,"best_legend_games":230,"best_legend_wins":149,"rating":2504,"tier":"Valhallan","games":230,"wins":149,"region":"EU","peak_rating":2533},{"rank":37,"name":"HaciTCH","brawlhalla_id":45653969,"best_legend":29,"best_legend_games":264,"best_legend_wins":165,"rating":2502,"tier":"Valhallan","games":264,"wins":165,"region":"EU","peak_rating":2502},{"rank":38,"name":"Bokonko","brawlhalla_id":55416094,"best_legend":16,"best_legend_games":483,"best_legend_wins":282,"rating":2501,"tier":"Valhallan","games":483,"wins":282,"region":"EU","peak_rating":2532},{"rank":39,"name":"happychappyiffy","brawlhalla_id":11488919,"best_legend":20,"best_legend_games":313,"best_legend_wins":210,"rating":2501,"tier":"Valhallan","games":313,"wins":210,"region":"EU","peak_rating":2501},{"rank":40,"name":"SM AGO$TINO","brawlhalla_id":34360305,"best_legend":20,"best_legend_games":303,"best_legend_wins":174,"rating":2500,"tier":"Valhallan","games":303,"wins":174,"region":"EU","peak_rating":2500},{"rank":41,"name":"Mounir","brawlhalla_id":31675679,"best_legend":40,"best_legend_games":129,"best_legend_wins":84,"rating":2500,"tier":"Diamond","games":129,"wins":84,"region":"EU","peak_rating":2518},{"rank":42,"name":"Flamethrower","brawlhalla_id":1447749,"best_legend":18,"best_legend_games":160,"best_legend_wins":108,"rating":2493,"tier":"Valhallan","games":160,"wins":108,"region":"EU","peak_rating":2521},{"rank":43,"name":"Pierre-Cha","brawlhalla_id":24778112,"best_legend":16,"best_legend_games":576,"best_legend_wins":344,"rating":2492,"tier":"Valhallan","games":576,"wins":344,"region":"EU","peak_rating":2495},{"rank":44,"name":"jett","brawlhalla_id":5218491,"best_legend":29,"best_legend_games":115,"best_legend_wins":81,"rating":2486,"tier":"Diamond","games":115,"wins":81,"region":"EU","peak_rating":2486},{"rank":45,"name":"KC | Fezaru80","brawlhalla_id":3540146,"best_legend":36,"best_legend_games":454,"best_legend_wins":263,"rating":2485,"tier":"Valhallan","games":454,"wins":263,"region":"EU","peak_rating":2529},{"rank":46,"name":"Neeze","brawlhalla_id":4423461,"best_legend":48,"best_legend_games":76,"best_legend_wins":60,"rating":2485,"tier":"Diamond","games":76,"wins":60,"region":"EU","peak_rating":2485},{"rank":47,"name":"digga","brawlhalla_id":2060440,"best_legend":16,"best_legend_games":242,"best_legend_wins":162,"rating":2481,"tier":"Valhallan","games":242,"wins":162,"region":"EU","peak_rating":2486},{"rank":48,"name":"M30W | Kresuu","brawlhalla_id":2926802,"best_legend":63,"best_legend_games":103,"best_legend_wins":70,"rating":2481,"tier":"Diamond","games":103,"wins":70,"region":"EU","peak_rating":2491},{"rank":49,"name":"Blitz","brawlhalla_id":65758824,"best_legend":16,"best_legend_games":147,"best_legend_wins":100,"rating":2480,"tier":"Valhallan","games":147,"wins":100,"region":"EU","peak_rating":2506},{"rank":50,"name":"JODEL6909","brawlhalla_id":14633994,"best_legend":22,"best_legend_games":165,"best_legend_wins":103,"rating":2477,"tier":"Valhallan","games":165,"wins":103,"region":"EU","peak_rating":2486},{"rank":51,"name":"im-Kawakii","brawlhalla_id":17799877,"best_legend":22,"best_legend_games":175,"best_legend_wins":102,"rating":2477,"tier":"Valhallan","games":175,"wins":102,"region":"EU","peak_rating":2509},{"rank":52,"name":"CRYPT_60Hz","brawlhalla_id":37730066,"best_legend":22,"best_legend_games":404,"best_legend_wins":243,"rating":2476,"tier":"Valhallan","games":404,"wins":243,"region":"EU","peak_rating":2525},{"rank":53,"name":"Akane?","brawlhalla_id":100755097,"best_legend":35,"best_legend_games":38,"best_legend_wins":33,"rating":2475,"tier":"Diamond","games":38,"wins":33,"region":"EU","peak_rating":2475},{"rank":54,"name":"Sagussy","brawlhalla_id":1034305,"best_legend":35,"best_legend_games":113,"best_legend_wins":79,"rating":2473,"tier":"Diamond","games":113,"wins":79,"region":"EU","peak_rating":2477},{"rank":55,"name":"KD | Blaze","brawlhalla_id":1766641,"best_legend":26,"best_legend_games":55,"best_legend_wins":44,"rating":2473,"tier":"Diamond","games":55,"wins":44,"region":"EU","peak_rating":2483},{"rank":56,"name":"kixè","brawlhalla_id":4570077,"best_legend":35,"best_legend_games":60,"best_legend_wins":43,"rating":2473,"tier":"Diamond","games":60,"wins":43,"region":"EU","peak_rating":2478},{"rank":57,"name":"kise","brawlhalla_id":49993518,"best_legend":16,"best_legend_games":125,"best_legend_wins":88,"rating":2471,"tier":"Diamond","games":125,"wins":88,"region":"EU","peak_rating":2471},{"rank":58,"name":"Adorable Kiwi 000194","brawlhalla_id":4868677,"best_legend":39,"best_legend_games":524,"best_legend_wins":293,"rating":2470,"tier":"Valhallan","games":524,"wins":293,"region":"EU","peak_rating":2483},{"rank":59,"name":"Tomas_fire973","brawlhalla_id":53033069,"best_legend":22,"best_legend_games":364,"best_legend_wins":248,"rating":2469,"tier":"Valhallan","games":364,"wins":248,"region":"EU","peak_rating":2503},{"rank":60,"name":"nebunu weed","brawlhalla_id":46070586,"best_legend":63,"best_legend_games":351,"best_legend_wins":200,"rating":2467,"tier":"Valhallan","games":351,"wins":200,"region":"EU","peak_rating":2475},{"rank":61,"name":"poison","brawlhalla_id":61010912,"best_legend":30,"best_legend_games":256,"best_legend_wins":160,"rating":2465,"tier":"Valhallan","games":256,"wins":160,"region":"EU","peak_rating":2508},{"rank":62,"name":"Kapp","brawlhalla_id":35464228,"best_legend":20,"best_legend_games":321,"best_legend_wins":186,"rating":2464,"tier":"Valhallan","games":321,"wins":186,"region":"EU","peak_rating":2506},{"rank":63,"name":"backverse","brawlhalla_id":63910800,"best_legend":54,"best_legend_games":161,"best_legend_wins":100,"rating":2464,"tier":"Valhallan","games":161,"wins":100,"region":"EU","peak_rating":2471},{"rank":64,"name":"KC | IceCream","brawlhalla_id":27433024,"best_legend":49,"best_legend_games":160,"best_legend_wins":97,"rating":2464,"tier":"Diamond","games":160,"wins":97,"region":"EU","peak_rating":2477},{"rank":65,"name":"Benjihyppääjä","brawlhalla_id":23890819,"best_legend":20,"best_legend_games":809,"best_legend_wins":436,"rating":2461,"tier":"Valhallan","games":809,"wins":436,"region":"EU","peak_rating":2461},{"rank":66,"name":"KC | Teoxys","brawlhalla_id":53674786,"best_legend":29,"best_legend_games":81,"best_legend_wins":57,"rating":2461,"tier":"Diamond","games":81,"wins":57,"region":"EU","peak_rating":2461},{"rank":67,"name":"Hanabi","brawlhalla_id":1219133,"best_legend":36,"best_legend_games":154,"best_legend_wins":99,"rating":2460,"tier":"Diamond","games":154,"wins":99,"region":"EU","peak_rating":2481},{"rank":68,"name":"Flawlëss","brawlhalla_id":49195794,"best_legend":50,"best_legend_games":184,"best_legend_wins":117,"rating":2459,"tier":"Valhallan","games":184,"wins":117,"region":"EU","peak_rating":2470},{"rank":69,"name":"Mijn Homie Tim","brawlhalla_id":6513665,"best_legend":31,"best_legend_games":217,"best_legend_wins":137,"rating":2458,"tier":"Valhallan","games":217,"wins":137,"region":"EU","peak_rating":2480},{"rank":70,"name":"RISK | ma2st4er5","brawlhalla_id":70022787,"best_legend":35,"best_legend_games":212,"best_legend_wins":121,"rating":2458,"tier":"Valhallan","games":212,"wins":121,"region":"EU","peak_rating":2458},{"rank":71,"name":"Hazlegs","brawlhalla_id":29971951,"best_legend":61,"best_legend_games":117,"best_legend_wins":74,"rating":2458,"tier":"Diamond","games":117,"wins":74,"region":"EU","peak_rating":2495},{"rank":72,"name":"Noah","brawlhalla_id":65131878,"best_legend":38,"best_legend_games":65,"best_legend_wins":52,"rating":2458,"tier":"Diamond","games":65,"wins":52,"region":"EU","peak_rating":2458},{"rank":73,"name":"bare?","brawlhalla_id":48936339,"best_legend":56,"best_legend_games":163,"best_legend_wins":100,"rating":2457,"tier":"Valhallan","games":163,"wins":100,"region":"EU","peak_rating":2469},{"rank":74,"name":"Linox","brawlhalla_id":6202261,"best_legend":50,"best_legend_games":69,"best_legend_wins":53,"rating":2457,"tier":"Diamond","games":69,"wins":53,"region":"EU","peak_rating":2457},{"rank":75,"name":"Sosa","brawlhalla_id":62014106,"best_legend":3,"best_legend_games":302,"best_legend_wins":202,"rating":2456,"tier":"Valhallan","games":302,"wins":202,"region":"EU","peak_rating":2456},{"rank":76,"name":"pera","brawlhalla_id":32568071,"best_legend":16,"best_legend_games":332,"best_legend_wins":190,"rating":2456,"tier":"Valhallan","games":332,"wins":190,"region":"EU","peak_rating":2465},{"rank":77,"name":"Philipp","brawlhalla_id":36499081,"best_legend":39,"best_legend_games":216,"best_legend_wins":135,"rating":2456,"tier":"Valhallan","games":216,"wins":135,"region":"EU","peak_rating":2456},{"rank":78,"name":"Lil'Skuurk","brawlhalla_id":74150212,"best_legend":39,"best_legend_games":160,"best_legend_wins":111,"rating":2456,"tier":"Valhallan","games":160,"wins":111,"region":"EU","peak_rating":2494},{"rank":79,"name":"Woop?","brawlhalla_id":1209176,"best_legend":16,"best_legend_games":62,"best_legend_wins":51,"rating":2455,"tier":"Diamond","games":62,"wins":51,"region":"EU","peak_rating":2460},{"rank":80,"name":"Urahara","brawlhalla_id":89437588,"best_legend":34,"best_legend_games":473,"best_legend_wins":279,"rating":2454,"tier":"Valhallan","games":473,"wins":279,"region":"EU","peak_rating":2481},{"rank":81,"name":"KC | TTVsimabh","brawlhalla_id":101904890,"best_legend":54,"best_legend_games":325,"best_legend_wins":183,"rating":2453,"tier":"Valhallan","games":325,"wins":183,"region":"EU","peak_rating":2506},{"rank":82,"name":"Nesqui[k] | \u003c3","brawlhalla_id":69289287,"best_legend":20,"best_legend_games":108,"best_legend_wins":66,"rating":2453,"tier":"Diamond","games":108,"wins":66,"region":"EU","peak_rating":2453},{"rank":83,"name":"Bwaka-SauWus's Wittle Strawbewy","brawlhalla_id":83385802,"best_legend":40,"best_legend_games":298,"best_legend_wins":175,"rating":2452,"tier":"Valhallan","games":298,"wins":175,"region":"EU","peak_rating":2452},{"rank":84,"name":"vVeyaax","brawlhalla_id":17545915,"best_legend":44,"best_legend_games":231,"best_legend_wins":137,"rating":2452,"tier":"Valhallan","games":231,"wins":137,"region":"EU","peak_rating":2454},{"rank":85,"name":"Skuurk","brawlhalla_id":5805481,"best_legend":16,"best_legend_games":756,"best_legend_wins":388,"rating":2451,"tier":"Valhallan","games":756,"wins":388,"region":"EU","peak_rating":2495},{"rank":86,"name":"1E-221 | Rexi S.","brawlhalla_id":7436252,"best_legend":61,"best_legend_games":160,"best_legend_wins":100,"rating":2451,"tier":"Valhallan","games":160,"wins":100,"region":"EU","peak_rating":2451},{"rank":87,"name":"ttv/volcano_stream","brawlhalla_id":93417167,"best_legend":54,"best_legend_games":960,"best_legend_wins":568,"rating":2448,"tier":"Valhallan","games":960,"wins":568,"region":"EU","peak_rating":2535},{"rank":88,"name":"Bleron","brawlhalla_id":10313538,"best_legend":4,"best_legend_games":319,"best_legend_wins":186,"rating":2445,"tier":"Valhallan","games":319,"wins":186,"region":"EU","peak_rating":2484},{"rank":89,"name":"arda güler \u003e barcelona","brawlhalla_id":96075266,"best_legend":42,"best_legend_games":286,"best_legend_wins":173,"rating":2445,"tier":"Valhallan","games":286,"wins":173,"region":"EU","peak_rating":2495},{"rank":90,"name":"harley","brawlhalla_id":35896326,"best_legend":10,"best_legend_games":110,"best_legend_wins":68,"rating":2445,"tier":"Diamond","games":110,"wins":68,"region":"EU","peak_rating":2445},{"rank":91,"name":"ianawad","brawlhalla_id":50104555,"best_legend":38,"best_legend_games":938,"best_legend_wins":556,"rating":2443,"tier":"Valhallan","games":938,"wins":556,"region":"EU","peak_rating":2496},{"rank":92,"name":"Dunezoner","brawlhalla_id":6721617,"best_legend":48,"best_legend_games":160,"best_legend_wins":100,"rating":2442,"tier":"Valhallan","games":160,"wins":100,"region":"EU","peak_rating":2451},{"rank":93,"name":"KC | Po","brawlhalla_id":73060643,"best_legend":40,"best_legend_games":95,"best_legend_wins":69,"rating":2440,"tier":"Diamond","games":95,"wins":69,"region":"EU","peak_rating":2455},{"rank":94,"name":"RISK | Avalanche","brawlhalla_id":34246622,"best_legend":64,"best_legend_games":257,"best_legend_wins":144,"rating":2439,"tier":"Valhallan","games":257,"wins":144,"region":"EU","peak_rating":2453},{"rank":95,"name":"hysen","brawlhalla_id":2333611,"best_legend":16,"best_legend_games":218,"best_legend_wins":138,"rating":2439,"tier":"Valhallan","games":218,"wins":138,"region":"EU","peak_rating":2467},{"rank":96,"name":"daaaa","brawlhalla_id":114296670,"best_legend":5,"best_legend_games":61,"best_legend_wins":50,"rating":2439,"tier":"Diamond","games":61,"wins":50,"region":"EU","peak_rating":2439},{"rank":97,"name":"ProbablyHighRee","brawlhalla_id":11116259,"best_legend":59,"best_legend_games":174,"best_legend_wins":102,"rating":2438,"tier":"Valhallan","games":174,"wins":102,"region":"EU","peak_rating":2453},{"rank":98,"name":"Akeno","brawlhalla_id":10336731,"best_legend":22,"best_legend_games":107,"best_legend_wins":67,"rating":2438,"tier":"Diamond","games":107,"wins":67,"region":"EU","peak_rating":2438},{"rank":99,"name":"Scythian Supremacy","brawlhalla_id":45276584,"best_legend":54,"best_legend_games":342,"best_legend_wins":203,"rating":2437,"tier":"Valhallan","games":342,"wins":203,"region":"EU","peak_rating":2459},{"rank":100,"name":"nesquik ekrem #UA","brawlhalla_id":4404065,"best_legend":10,"best_legend_games":223,"best_legend_wins":128,"rating":2437,"tier":"Valhallan","games":223,"wins":128,"region":"EU","peak_rating":2437},{"rank":101,"name":"Vlo0lyy","brawlhalla_id":89826480,"best_legend":3,"best_legend_games":313,"best_legend_wins":178,"rating":2435,"tier":"Valhallan","games":313,"wins":178,"region":"EU","peak_rating":2453},{"rank":102,"name":"Spires","brawlhalla_id":115903642,"best_legend":44,"best_legend_games":141,"best_legend_wins":109,"rating":2435,"tier":"Valhallan","games":141,"wins":109,"region":"EU","peak_rating":2435},{"rank":103,"name":"anto123arci","brawlhalla_id":36103988,"best_legend":37,"best_legend_games":171,"best_legend_wins":100,"rating":2435,"tier":"Valhallan","games":171,"wins":100,"region":"EU","peak_rating":2490},{"rank":104,"name":"akiin","brawlhalla_id":3517230,"best_legend":31,"best_legend_games":139,"best_legend_wins":88,"rating":2435,"tier":"Diamond","games":139,"wins":88,"region":"EU","peak_rating":2442},{"rank":105,"name":"choccy","brawlhalla_id":75708768,"best_legend":40,"best_legend_games":661,"best_legend_wins":425,"rating":2434,"tier":"Valhallan","games":661,"wins":425,"region":"EU","peak_rating":2498},{"rank":106,"name":"Godwin","brawlhalla_id":71792327,"best_legend":20,"best_legend_games":653,"best_legend_wins":351,"rating":2434,"tier":"Valhallan","games":653,"wins":351,"region":"EU","peak_rating":2444},{"rank":107,"name":"SlownzInAbyss","brawlhalla_id":95974513,"best_legend":16,"best_legend_games":255,"best_legend_wins":135,"rating":2434,"tier":"Valhallan","games":255,"wins":135,"region":"EU","peak_rating":2436},{"rank":108,"name":"SiB | wave god","brawlhalla_id":2015782,"best_legend":20,"best_legend_games":61,"best_legend_wins":47,"rating":2434,"tier":"Diamond","games":68,"wins":49,"region":"EU","peak_rating":2439},{"rank":109,"name":"Khinger","brawlhalla_id":8474197,"best_legend":42,"best_legend_games":930,"best_legend_wins":516,"rating":2433,"tier":"Valhallan","games":930,"wins":516,"region":"EU","peak_rating":2535},{"rank":110,"name":"Tengen","brawlhalla_id":12496336,"best_legend":29,"best_legend_games":115,"best_legend_wins":69,"rating":2433,"tier":"Diamond","games":115,"wins":69,"region":"EU","peak_rating":2438},{"rank":111,"name":"CaSp","brawlhalla_id":709858,"best_legend":54,"best_legend_games":181,"best_legend_wins":111,"rating":2432,"tier":"Valhallan","games":181,"wins":111,"region":"EU","peak_rating":2454},{"rank":112,"name":"VoDr","brawlhalla_id":71668185,"best_legend":16,"best_legend_games":101,"best_legend_wins":67,"rating":2432,"tier":"Diamond","games":101,"wins":67,"region":"EU","peak_rating":2432},{"rank":113,"name":"KiingCriiimson","brawlhalla_id":57182157,"best_legend":20,"best_legend_games":353,"best_legend_wins":208,"rating":2431,"tier":"Valhallan","games":353,"wins":208,"region":"EU","peak_rating":2431},{"rank":114,"name":"Goofy","brawlhalla_id":4070196,"best_legend":59,"best_legend_games":244,"best_legend_wins":140,"rating":2431,"tier":"Valhallan","games":244,"wins":140,"region":"EU","peak_rating":2436},{"rank":115,"name":"jhafmega","brawlhalla_id":9084431,"best_legend":33,"best_legend_games":136,"best_legend_wins":83,"rating":2430,"tier":"Diamond","games":136,"wins":83,"region":"EU","peak_rating":2430},{"rank":116,"name":"hooligan445","brawlhalla_id":32113409,"best_legend":15,"best_legend_games":75,"best_legend_wins":49,"rating":2430,"tier":"Diamond","games":75,"wins":49,"region":"EU","peak_rating":2438},{"rank":117,"name":"lsejx","brawlhalla_id":11971299,"best_legend":3,"best_legend_games":90,"best_legend_wins":63,"rating":2429,"tier":"Diamond","games":90,"wins":63,"region":"EU","peak_rating":2440},{"rank":118,"name":"abolaji","brawlhalla_id":28210139,"best_legend":6,"best_legend_games":341,"best_legend_wins":234,"rating":2428,"tier":"Valhallan","games":341,"wins":234,"region":"EU","peak_rating":2463},{"rank":119,"name":"RISK | Peter Griffin","brawlhalla_id":39636161,"best_legend":40,"best_legend_games":414,"best_legend_wins":266,"rating":2427,"tier":"Valhallan","games":414,"wins":266,"region":"EU","peak_rating":2427},{"rank":120,"name":"random mordex opp","brawlhalla_id":24737524,"best_legend":35,"best_legend_games":240,"best_legend_wins":142,"rating":2427,"tier":"Valhallan","games":240,"wins":142,"region":"EU","peak_rating":2468},{"rank":121,"name":"repl0yz-_-","brawlhalla_id":19333135,"best_legend":20,"best_legend_games":213,"best_legend_wins":124,"rating":2426,"tier":"Valhallan","games":213,"wins":124,"region":"EU","peak_rating":2428},{"rank":122,"name":"xEdit1","brawlhalla_id":10937218,"best_legend":11,"best_legend_games":322,"best_legend_wins":179,"rating":2424,"tier":"Valhallan","games":322,"wins":179,"region":"EU","peak_rating":2424},{"rank":123,"name":"Playboi Carti","brawlhalla_id":7364605,"best_legend":20,"best_legend_games":181,"best_legend_wins":110,"rating":2424,"tier":"Valhallan","games":181,"wins":110,"region":"EU","peak_rating":2449},{"rank":124,"name":"sætre","brawlhalla_id":8505150,"best_legend":20,"best_legend_games":160,"best_legend_wins":98,"rating":2424,"tier":"Diamond","games":160,"wins":98,"region":"EU","peak_rating":2424},{"rank":125,"name":"bartu son","brawlhalla_id":62051982,"best_legend":54,"best_legend_games":28,"best_legend_wins":25,"rating":2424,"tier":"Diamond","games":28,"wins":25,"region":"EU","peak_rating":2426},{"rank":126,"name":"EssJay","brawlhalla_id":3527363,"best_legend":46,"best_legend_games":227,"best_legend_wins":139,"rating":2423,"tier":"Valhallan","games":227,"wins":139,"region":"EU","peak_rating":2428},{"rank":127,"name":"Börkii the börkiiest Pikachu","brawlhalla_id":453250,"best_legend":25,"best_legend_games":201,"best_legend_wins":118,"rating":2423,"tier":"Valhallan","games":201,"wins":118,"region":"EU","peak_rating":2431},{"rank":128,"name":"Eric","brawlhalla_id":3117608,"best_legend":40,"best_legend_games":353,"best_legend_wins":190,"rating":2422,"tier":"Valhallan","games":353,"wins":190,"region":"EU","peak_rating":2459},{"rank":129,"name":"l-9speedMako-l","brawlhalla_id":89083270,"best_legend":54,"best_legend_games":162,"best_legend_wins":101,"rating":2422,"tier":"Valhallan","games":162,"wins":101,"region":"EU","peak_rating":2422},{"rank":130,"name":"xo","brawlhalla_id":95742615,"best_legend":16,"best_legend_games":113,"best_legend_wins":70,"rating":2422,"tier":"Diamond","games":137,"wins":80,"region":"EU","peak_rating":2437},{"rank":131,"name":"xDxablo","brawlhalla_id":23334361,"best_legend":22,"best_legend_games":700,"best_legend_wins":328,"rating":2421,"tier":"Valhallan","games":700,"wins":328,"region":"EU","peak_rating":2578},{"rank":132,"name":"Blaser","brawlhalla_id":4200861,"best_legend":16,"best_legend_games":185,"best_legend_wins":124,"rating":2421,"tier":"Valhallan","games":185,"wins":124,"region":"EU","peak_rating":2421},{"rank":133,"name":"Jenos","brawlhalla_id":104803147,"best_legend":30,"best_legend_games":164,"best_legend_wins":101,"rating":2421,"tier":"Valhallan","games":164,"wins":101,"region":"EU","peak_rating":2421},{"rank":134,"name":"Satoko","brawlhalla_id":4454684,"best_legend":48,"best_legend_games":79,"best_legend_wins":48,"rating":2421,"tier":"Diamond","games":96,"wins":56,"region":"EU","peak_rating":2421},{"rank":135,"name":"😈Hector Helio","brawlhalla_id":78156512,"best_legend":3,"best_legend_games":57,"best_legend_wins":37,"rating":2421,"tier":"Diamond","games":57,"wins":37,"region":"EU","peak_rating":2421},{"rank":136,"name":"Snoopy","brawlhalla_id":3689475,"best_legend":20,"best_legend_games":200,"best_legend_wins":114,"rating":2420,"tier":"Valhallan","games":200,"wins":114,"region":"EU","peak_rating":2420},{"rank":137,"name":"JokyyFREEZINGCOLD","brawlhalla_id":1471617,"best_legend":26,"best_legend_games":73,"best_legend_wins":53,"rating":2420,"tier":"Diamond","games":73,"wins":53,"region":"EU","peak_rating":2420},{"rank":138,"name":"Taher#FreePalestine","brawlhalla_id":2937369,"best_legend":51,"best_legend_games":655,"best_legend_wins":346,"rating":2419,"tier":"Valhallan","games":655,"wins":346,"region":"EU","peak_rating":2433},{"rank":139,"name":"Destper's wife","brawlhalla_id":29674781,"best_legend":54,"best_legend_games":351,"best_legend_wins":203,"rating":2419,"tier":"Valhallan","games":351,"wins":203,"region":"EU","peak_rating":2419},{"rank":140,"name":"55p.green.tea","brawlhalla_id":5708299,"best_legend":31,"best_legend_games":265,"best_legend_wins":143,"rating":2419,"tier":"Valhallan","games":265,"wins":143,"region":"EU","peak_rating":2435},{"rank":141,"name":"bvvfghnbgggtrred","brawlhalla_id":15201742,"best_legend":12,"best_legend_games":176,"best_legend_wins":105,"rating":2419,"tier":"Valhallan","games":176,"wins":105,"region":"EU","peak_rating":2419},{"rank":142,"name":"WAAS","brawlhalla_id":97533867,"best_legend":20,"best_legend_games":62,"best_legend_wins":47,"rating":2419,"tier":"Diamond","games":62,"wins":47,"region":"EU","peak_rating":2425},{"rank":143,"name":"cheezy","brawlhalla_id":79196881,"best_legend":16,"best_legend_games":534,"best_legend_wins":286,"rating":2418,"tier":"Valhallan","games":534,"wins":286,"region":"EU","peak_rating":2442},{"rank":144,"name":"trqns killer #1","brawlhalla_id":87836918,"best_legend":54,"best_legend_games":255,"best_legend_wins":144,"rating":2418,"tier":"Valhallan","games":255,"wins":144,"region":"EU","peak_rating":2435},{"rank":145,"name":"Zeltol","brawlhalla_id":9279884,"best_legend":61,"best_legend_games":186,"best_legend_wins":109,"rating":2418,"tier":"Valhallan","games":186,"wins":109,"region":"EU","peak_rating":2418},{"rank":146,"name":"Starkli","brawlhalla_id":77905708,"best_legend":31,"best_legend_games":149,"best_legend_wins":101,"rating":2418,"tier":"Valhallan","games":149,"wins":101,"region":"EU","peak_rating":2418},{"rank":147,"name":"Cedero","brawlhalla_id":208328,"best_legend":20,"best_legend_games":83,"best_legend_wins":57,"rating":2418,"tier":"Diamond","games":83,"wins":57,"region":"EU","peak_rating":2424},{"rank":148,"name":"savoka","brawlhalla_id":8341584,"best_legend":39,"best_legend_games":230,"best_legend_wins":127,"rating":2417,"tier":"Diamond","games":230,"wins":127,"region":"EU","peak_rating":2443},{"rank":149,"name":"Sweaty","brawlhalla_id":91520268,"best_legend":38,"best_legend_games":534,"best_legend_wins":286,"rating":2416,"tier":"Diamond","games":534,"wins":286,"region":"EU","peak_rating":2425},{"rank":150,"name":"Ayaojee","brawlhalla_id":36962309,"best_legend":50,"best_legend_games":423,"best_legend_wins":230,"rating":2416,"tier":"Valhallan","games":423,"wins":230,"region":"EU","peak_rating":2437}]